zjt_sun/__init__.py
zjt_sun-0.1.0.dist-info/WHEEL
zjt_sun-0.1.0.dist-info/entry_points.txt
zjt_sun-0.1.0.dist-info/METADATA
zjt_sun-0.1.0.dist-info/RECORD
