Metadata-Version: 2.3
Name: zjt-sun
Version: 0.1.0
Summary: Add your description here
Author: zjt
Author-email: zjt <acpmbe@qq.com>
Requires-Dist: mcp[cli]>=1.20.0
Requires-Python: >=3.14
